[
  {
    "postId": "587c659e15d7228addd4e8dc",
    "postBody": "est qui nostrud commodo ex excepteur sunt enim consequat cupidatat",
    "timestamp": "Sat Dec 08 2012 19:23:45 GMT+0000 (UTC)",
    "avatar": "avi/Alice1.jpg",
    "username": "Ofelia Spears",
    "privacy": "public"
  },
  {
    "postId": "587c659e491fae6b9f9fc3c1",
    "postBody": "amet exercitation adipisicing exercitation nisi commodo et reprehenderit aute esse",
    "timestamp": "Sun Mar 13 2011 10:08:16 GMT+0000 (UTC)",
    "avatar": "avi/Alex.png",
    "username": "Whitley Frye",
    "privacy": "public"
  },
  {
    "postId": "587c659edc4b19526ee253eb",
    "postBody": "aute non excepteur voluptate esse sint non nulla in id",
    "timestamp": "Thu Jan 21 2010 22:05:44 GMT+0000 (UTC)",
    "avatar": "avi/banekoma.png",
    "username": "Kerr Brennan",
    "privacy": "private"
  },
  {
    "postId": "587c659e36ba1f9867e42c7c",
    "postBody": "pariatur excepteur laborum irure nostrud cillum ea cillum magna ea",
    "timestamp": "Mon Mar 09 2009 12:33:28 GMT+0000 (UTC)",
    "avatar": "avi/Geri.jpg",
    "username": "Bettie Lawrence",
    "privacy": "private"
  },
  {
    "postId": "587c659e0924035d3abf377d",
    "postBody": "qui sit dolore consequat adipisicing ad ad exercitation elit aliqua",
    "timestamp": "Sat Apr 01 2000 07:22:37 GMT+0000 (UTC)",
    "avatar": "avi/Tomek.jpg",
    "username": "Anthony Church",
    "privacy": "private"
  },
  {
    "postId": "587c659e792587cf469846dd",
    "postBody": "voluptate aute pariatur quis Lorem eu sit ad laboris officia",
    "timestamp": "Wed Feb 25 1998 14:06:02 GMT+0000 (UTC)",
    "avatar": "avi/Val.png",
    "username": "Natalia Mckee",
    "privacy": "private"
  },
  {
    "postId": "587c659ebd231982bca3e483",
    "postBody": "sint sunt nisi consectetur tempor do incididunt aliqua duis officia",
    "timestamp": "Mon Jul 07 1986 11:40:14 GMT+0000 (UTC)",
    "avatar": "avi/Jack.jpg",
    "username": "Odom Castaneda",
    "privacy": "private"
  },
  {
    "postId": "587c659e7823d4bc53f5515b",
    "postBody": "quis laborum mollit aliquip sunt commodo officia fugiat do magna",
    "timestamp": "Wed May 14 1980 17:04:13 GMT+0000 (UTC)",
    "avatar": "avi/Katerina.jpg",
    "username": "Kristine Estrada",
    "privacy": "private"
  },
  {
    "postId": "587c659e73f45aa06771dcd9",
    "postBody": "sint quis culpa magna exercitation consectetur do duis excepteur ullamco",
    "timestamp": "Sat Dec 29 1979 01:25:11 GMT+0000 (UTC)",
    "avatar": "avi/Rob.jpg",
    "username": "Beasley Salas",
    "privacy": "public"
  },
  {
    "postId": "587c659e40544c9f1ead8c94",
    "postBody": "sint elit minim cillum exercitation magna sunt ipsum cillum incididunt",
    "timestamp": "Sat Feb 06 1971 01:35:08 GMT+0000 (UTC)",
    "avatar": "avi/nick.jpg",
    "username": "Josefa Chang",
    "privacy": "public"
  }
]